{
	"name": "SourceDataset_5qk",
	"properties": {
		"linkedServiceName": {
			"referenceName": "AzureBlobStorage1",
			"type": "LinkedServiceReference"
		},
		"annotations": [],
		"type": "DelimitedText",
		"typeProperties": {
			"location": {
				"type": "AzureBlobStorageLocation",
				"fileName": "Trader_Master.csv",
				"container": "master"
			},
			"columnDelimiter": ",",
			"escapeChar": "\\",
			"firstRowAsHeader": true,
			"quoteChar": "\""
		},
		"schema": [
			{
				"name": "Trader_No",
				"type": "String"
			},
			{
				"name": "Trader_Code",
				"type": "String"
			},
			{
				"name": "Group_Trader_Code",
				"type": "String"
			},
			{
				"name": "Company_No.",
				"type": "String"
			},
			{
				"name": "Corporation_No.",
				"type": "String"
			},
			{
				"name": "Trader_Map_Key",
				"type": "String"
			},
			{
				"name": "TRD_ORG_DSCTN",
				"type": "String"
			},
			{
				"name": "TRD_MNGR_NAME",
				"type": "String"
			},
			{
				"name": "Trader_Email",
				"type": "String"
			},
			{
				"name": "Trader_Name",
				"type": "String"
			},
			{
				"name": "Trader_State",
				"type": "String"
			},
			{
				"name": "Trader_City",
				"type": "String"
			},
			{
				"name": "Trader_Region",
				"type": "String"
			},
			{
				"name": "TRD_Main_Dealer",
				"type": "String"
			},
			{
				"name": "Traders",
				"type": "String"
			},
			{
				"name": "Area_Manager",
				"type": "String"
			},
			{
				"name": "TRD_SPR_TRD_CODE",
				"type": "String"
			},
			{
				"name": "TRD_DSCTN",
				"type": "String"
			}
		]
	}
}